README.md
setup.py
PriorityThreadPoolExecutor/__init__.py
PriorityThreadPoolExecutor.egg-info/PKG-INFO
PriorityThreadPoolExecutor.egg-info/SOURCES.txt
PriorityThreadPoolExecutor.egg-info/dependency_links.txt
PriorityThreadPoolExecutor.egg-info/top_level.txt